pylambder/__init__.py
pylambder/aws_task.py
pylambder/base.py
pylambder/cli.py
pylambder/config.py
pylambder/websocket.py
pylambder/configuration/__init__.py
pylambder/configuration/configuration.py
pylambder/configuration/user_config_template.py
pylambder/packaged/authorizer.zip
pylambder/packaged/onconnect.zip
pylambder/packaged/ondisconnect.zip
pylambder/packaged/taskexecute.zip
pylambder/packaged/taskresult.zip
pylambder/packaging/__init__.py
pylambder/packaging/aws.py
pylambder/packaging/deployment.py
pylambder/packaging/packaging.py
pylambder/sam-data/.gitignore
pylambder/sam-data/README.md
pylambder/sam-data/template.yaml.template
pylambder/sam-data/.idea/misc.xml
pylambder/sam-data/.idea/modules.xml
pylambder/sam-data/.idea/sam-app.iml
pylambder/sam-data/.idea/vcs.xml
pylambder/sam-data/authorizer/handler.py
pylambder/sam-data/onconnect/handler.py
pylambder/sam-data/ondisconnect/handler.py
pylambder/sam-data/taskexecute/handler.py
pylambder/sam-data/taskresult/handler.py
sample/__init__.py
sample/app.py
pylambder-0.2.1.dist-info/LICENSE
pylambder-0.2.1.dist-info/METADATA
pylambder-0.2.1.dist-info/WHEEL
pylambder-0.2.1.dist-info/entry_points.txt
pylambder-0.2.1.dist-info/top_level.txt
pylambder-0.2.1.dist-info/RECORD
