Metadata-Version: 2.1
Name: pylambder
Version: 0.2.1
Summary: Remote task execution on AWS Lambda for Python
Home-page: UNKNOWN
Author: Wojciech Geisler, Artur Jopek
Author-email: wojciech.geisler@gmail.com
License: UNKNOWN
Keywords: task aws lambda
Platform: UNKNOWN
Classifier: Development Status :: 2 - Pre-Alpha
Classifier: Intended Audience :: Developers
Classifier: Topic :: System :: Distributed Computing
Classifier: License :: OSI Approved :: MIT License
Classifier: Programming Language :: Python :: 3
Classifier: Programming Language :: Python :: 3.7
Requires-Python: >= 3.7, <4
Requires-Dist: boto3 (>=1.9.210)
Requires-Dist: websockets (~=8.0)
Requires-Dist: janus (==0.4.0)
Provides-Extra: dev
Requires-Dist: pylint ; extra == 'dev'
Provides-Extra: test
